pasvg/__init__.py
pasvg/cli.py
pasvg/pasvg_build_system.py
pasvg/pasvg_extractor.py
pasvg/pasvg_extractor_fixed.py
pasvg/pasvg_generator.py
pasvg/core/__init__.py
pasvg/core/builder.py
pasvg/core/extractor.py
pasvg/core/generator.py
pasvg/core/models.py
pasvg/core/validator.py
pasvg/generators/__init__.py
pasvg/generators/build_script_generator.py
pasvg/generators/svg_renderer.py
pasvg/importers/__init__.py
pasvg/importers/markdown_importer.py
pasvg/utils/__init__.py
pasvg/utils/file_utils/__init__.py
pasvg/utils/file_utils/file_operations.py
pasvg/utils/file_utils/file_scanner.py
pasvg/utils/file_utils/file_validator.py
pasvg/utils/file_utils/types.py
pasvg-1.0.8.dist-info/METADATA
pasvg-1.0.8.dist-info/WHEEL
pasvg-1.0.8.dist-info/entry_points.txt
pasvg-1.0.8.dist-info/RECORD
