Metadata-Version: 2.4
Name: pasvg
Version: 1.0.8
Summary: Project Artifact SVG - Revolutionary single-file project distribution system
Project-URL: Homepage, https://github.com/dynapsys/pasvg
Project-URL: Documentation, https://github.com/dynapsys/pasvg/tree/main/docs
Project-URL: Repository, https://github.com/dynapsys/pasvg
Project-URL: Issues, https://github.com/dynapsys/pasvg/issues
Author-email: Tom Sapletta <info@softreck.dev>
License-Expression: Apache-2.0
Keywords: automation,build-system,container,deployment,project-artifact,single-file,svg
Classifier: Development Status :: 5 - Production/Stable
Classifier: Intended Audience :: Developers
Classifier: License :: OSI Approved :: Apache Software License
Classifier: Programming Language :: Python :: 3
Classifier: Programming Language :: Python :: 3.8
Classifier: Programming Language :: Python :: 3.9
Classifier: Programming Language :: Python :: 3.10
Classifier: Programming Language :: Python :: 3.11
Classifier: Programming Language :: Python :: 3.12
Classifier: Topic :: Software Development :: Build Tools
Classifier: Topic :: Software Development :: Code Generators
Classifier: Topic :: Text Processing :: Markup :: XML
Requires-Python: >=3.8
Requires-Dist: click>=8.0.0
Requires-Dist: jinja2>=3.0.0
Requires-Dist: pathlib-abc>=0.1.0
Requires-Dist: pyyaml>=6.0
Provides-Extra: dev
Requires-Dist: black>=22.0.0; extra == 'dev'
Requires-Dist: flake8>=5.0.0; extra == 'dev'
Requires-Dist: isort>=5.10.0; extra == 'dev'
Requires-Dist: mypy>=1.0.0; extra == 'dev'
Requires-Dist: pytest-cov>=4.0.0; extra == 'dev'
Requires-Dist: pytest>=7.0.0; extra == 'dev'
